pyqsartoolbox/__init__.py
pyqsartoolbox/qsartoolbox.py
pyqsartoolbox-0.1.0.dist-info/METADATA
pyqsartoolbox-0.1.0.dist-info/WHEEL
pyqsartoolbox-0.1.0.dist-info/top_level.txt
pyqsartoolbox-0.1.0.dist-info/RECORD
