Metadata-Version: 2.4
Name: pyqsartoolbox
Version: 0.1.0
Summary: Python client for the local QSAR Toolbox Web API
Author-email: "Ali A. Eftekhari" <e.eftekhari@gmail.com>
License-Expression: MIT
Project-URL: Homepage, https://github.com/USEtox/PyQSARToolbox
Project-URL: Documentation, https://usetox.github.io/PyQSARToolbox/
Classifier: Programming Language :: Python :: 3
Classifier: Programming Language :: Python :: 3.9
Classifier: Intended Audience :: Science/Research
Classifier: Topic :: Scientific/Engineering :: Chemistry
Classifier: Operating System :: OS Independent
Requires-Python: >=3.9
Requires-Dist: requests>=2.31.0
Requires-Dist: pandas>=1.5.0
Provides-Extra: dev
Requires-Dist: pytest>=8.2; extra == "dev"
Requires-Dist: pytest-cov>=5.0; extra == "dev"
Requires-Dist: mkdocs>=1.5; extra == "dev"
Requires-Dist: mkdocs-material>=9.5; extra == "dev"
Requires-Dist: mkdocstrings[python]>=0.25; extra == "dev"
Requires-Dist: ruff>=0.5.0; extra == "dev"
Provides-Extra: docs
Requires-Dist: mkdocs>=1.5; extra == "docs"
Requires-Dist: mkdocs-material>=9.5; extra == "docs"
Requires-Dist: mkdocstrings[python]>=0.25; extra == "docs"
Provides-Extra: test
Requires-Dist: pytest>=8.2; extra == "test"
Requires-Dist: pytest-cov>=5.0; extra == "test"
